odoo/addons/server_environment_data_encryption/README.rst
odoo/addons/server_environment_data_encryption/__init__.py
odoo/addons/server_environment_data_encryption/__manifest__.py
odoo/addons/server_environment_data_encryption/i18n/ca.po
odoo/addons/server_environment_data_encryption/i18n/es.po
odoo/addons/server_environment_data_encryption/i18n/it.po
odoo/addons/server_environment_data_encryption/i18n/server_environment_data_encryption.pot
odoo/addons/server_environment_data_encryption/i18n/sv.po
odoo/addons/server_environment_data_encryption/models/__init__.py
odoo/addons/server_environment_data_encryption/models/server_env_mixin.py
odoo/addons/server_environment_data_encryption/readme/CONFIGURE.md
odoo/addons/server_environment_data_encryption/readme/CONTRIBUTORS.md
odoo/addons/server_environment_data_encryption/readme/DESCRIPTION.md
odoo/addons/server_environment_data_encryption/static/description/icon.png
odoo/addons/server_environment_data_encryption/static/description/index.html
odoo/addons/server_environment_data_encryption/tests/__init__.py
odoo/addons/server_environment_data_encryption/tests/models.py
odoo/addons/server_environment_data_encryption/tests/test_server_environment_data_encrypt.py
odoo/addons/server_environment_data_encryption/tests/fixtures/base.xml
odoo_addon_server_environment_data_encryption-18.0.1.0.0.5.dist-info/METADATA
odoo_addon_server_environment_data_encryption-18.0.1.0.0.5.dist-info/WHEEL
odoo_addon_server_environment_data_encryption-18.0.1.0.0.5.dist-info/top_level.txt
odoo_addon_server_environment_data_encryption-18.0.1.0.0.5.dist-info/RECORD
